python_rdio_export-1.3.0.data/scripts/rdio-export
python_rdio_export-1.3.0.dist-info/DESCRIPTION.rst
python_rdio_export-1.3.0.dist-info/METADATA
python_rdio_export-1.3.0.dist-info/metadata.json
python_rdio_export-1.3.0.dist-info/RECORD
python_rdio_export-1.3.0.dist-info/top_level.txt
python_rdio_export-1.3.0.dist-info/WHEEL
rdio_export/__init__.py
rdio_export/exporter.py
