Metadata-Version: 2.0
Name: python-rdio-export
Version: 1.3.0
Summary: A command-line utility for exporting an Rdio collection.
Home-page: https://github.com/twaddington/python-rdio-export
Author: Tristan Waddington
Author-email: tristan.waddington@gmail.com
License:                                  Apache License
Requires-Dist: requests
Requires-Dist: requests-oauthlib
